database_pool/__init__.py
database_pool/backends/__init__.py
database_pool/backends/mysql/__init__.py
database_pool/backends/mysql/base.py
database_pool/backends/oracle/__init__.py
database_pool/backends/oracle/base.py
database_pool/backends/oracle/creation.py
database_pool/backends/oracle/log_sql.py
database_pool/backends/oracle/pool.py
database_pool/backends/oracle/utils.py
database_pool/backends/postgresql/__init__.py
database_pool/backends/postgresql/base.py
database_pool/backends/postgresql/pool.py
database_pool/core/__init__.py
database_pool/core/exceptions.py
database_pool/core/mixins.py
db_pool_demo/__init__.py
db_pool_demo/settings.py
db_pool_demo/urls.py
db_pool_demo/wsgi.py
db_pool_demo/app_demo/__init__.py
db_pool_demo/app_demo/admin.py
db_pool_demo/app_demo/apps.py
db_pool_demo/app_demo/models.py
db_pool_demo/app_demo/tests.py
db_pool_demo/app_demo/views.py
db_pool_demo/app_demo/migrations/0001_initial.py
db_pool_demo/app_demo/migrations/0002_pooldemomodel_remark_alter_pooldemomodel_name.py
db_pool_demo/app_demo/migrations/0003_alter_pooldemomodel_id.py
db_pool_demo/app_demo/migrations/0004_pooldemomodel_db_type.py
db_pool_demo/app_demo/migrations/__init__.py
django_database_conn_pool-1.1.1.dist-info/LICENSE
django_database_conn_pool-1.1.1.dist-info/METADATA
django_database_conn_pool-1.1.1.dist-info/WHEEL
django_database_conn_pool-1.1.1.dist-info/top_level.txt
django_database_conn_pool-1.1.1.dist-info/RECORD
