Metadata-Version: 2.1
Name: django-database-conn-pool
Version: 1.1.1
Summary: django database backend pooling for connections
Home-page: https://github.com/luojidr/django-database-pool
Author: luojidr
Author-email: luojidr@163.com
Maintainer: luojidr
Maintainer-email: luojidr@163.com
License: MIT
Keywords: django connection pooling mysql postgresql cx_Oracle
Classifier: Programming Language :: Python :: 3.7
Classifier: Programming Language :: Python :: 3.8
Classifier: Programming Language :: Python :: 3.9
Classifier: Programming Language :: Python :: 3.10
Classifier: Framework :: Django :: 3
Classifier: Framework :: Django :: 4.0
Classifier: License :: OSI Approved :: MIT License
Classifier: Topic :: Software Development :: Libraries :: Python Modules
Classifier: Intended Audience :: Developers
License-File: LICENSE
Requires-Dist: django (<=4.0.8,>=3.0)
Requires-Dist: sqlalchemy (==1.4.44)
Requires-Dist: cx-Oracle (==8.3.0)
Requires-Dist: psycopg2 (==2.9.5)
